{
  "id": "169c58128660b30758c0d89043f26a9f174cee0d085284df68e075e2339808d7",
  "url": "https://journal.burningman.org/2018/09/black-rock-city/leaving-no-trace/moop-map-2018-day-3-so-far-so-good/",
  "title": "MOOP MAP 2018: Day 3 – So Far, So Good",
  "author": "DA",
  "dateISO": "2018-09-26T08:46:01-07:00",
  "content": "MOOP MAP 2018 Day 3 : Wednesday, September 19, 2018\n\nTotal Crew on Playa: 164\n\nCity Grid Blocks Completed: 3:30 to 10:00 Esplanade-A, AB, BC\n\nLocation: Black Rock City, NV\n\nWeather: Sunny, clear\n\nTemperature: 73°/36°\n\nWind: 0-16 mph\n\nPlaya Restoration All-Star Team: Line Sweeps photography by Moon Mandel, edited by DA\n\nThe MOOP Map Scribes, after a long day in the field, meet to transcribe their gps data to the MOOP Map. Video by DA\n\nAs always, the MOOP Map is a work in progress and a final hi-res version will be made available only after we’ve completed our work on the playa, reviewed all of our data, and verified that all of the Theme Camps are in their final correct placement.\n\nIf you are the official leader/contact of a theme camp and would like to request a MOOP Report you can do so by filling out a MOOP Report Request Form. Due to high demand from Green camps with a little bit of Red, priority will be given to Red camps.",
  "source": "burningman_journal",
  "category": "black-rock-city",
  "topic": "leaving-no-trace"
}