{
  "id": "3ff655784ddcf046a0eded5240a312ffcc6755ed2af3af51ffe35bbc4bfc707c",
  "url": "https://journal.burningman.org/2011/07/burning-man-arts/global-art/fashion-from-moscow/",
  "title": "Fashion from Moscow",
  "author": "Affinity",
  "dateISO": "2011-07-18T14:05:04-07:00",
  "content": "One of the [BRAF]’s 2009 Grantees, Cardboardia in Moscow, put on a Haute Couture Fashion Show recently and it is delightful. It put a big smile on my face!",
  "source": "burningman_journal",
  "category": "burning-man-arts",
  "topic": "global-art"
}