{
  "id": "586f93d141f3dbf4c6a0f53a142ca864cfe7a5c4e31d53b463ad5d4b73ff6bde",
  "url": "https://journal.burningman.org/2018/08/news/brc-news/eis-deadline-tomorrow/",
  "title": "Make Your Voice Heard in Our 10-Year Environmental Impact Process — Deadline August 4",
  "author": "Burning Man Project",
  "dateISO": "2018-08-03T16:22:34-07:00",
  "content": "Burning Man is applying for a 10-year permit with the Bureau of Land Management to ensure our future building Black Rock City in the Black Rock Desert, and we need your help!\n\nThe Environmental Impact Statement process examines a range of issues and how they affect the environment, the surrounding communities and the government’s ability to manage the Special Recreation Permit that Burning Man operates under. We’re asking for your supportive comments by the deadline of Saturday, August 4 at 11pm PST. We hope Burning Man has made a difference in your life and you will take a moment to send us some love.\n\nEmail is the best way to have your voice heard. Send your message to BLM_NV_BurningManEIS@blm.gov and include “Burning Man SRP EIS Comments” in the subject line.\n\nYou can write a general message of support for the event and our community, but substantive comments are the most helpful to the EIS process. Key areas of interest in the EIS process include:\n\nYour advocacy is essential in this process. The deadline for emailing your comments is Saturday, August 4 at 11pm PST, so please send the Bureau of Land Management a message right this minute!\n\n(Top photo by John Stephen Chandler)",
  "source": "burningman_journal",
  "category": "news",
  "topic": "brc-news"
}