{
  "id": "abd24ceee5bbe721e8336bd4c9abcb37d572149fa3c7ab107d2c9a6db45acfb6",
  "url": "https://journal.burningman.org/2012/04/global-network/global-programming/burning-man-at-the-conference-on-world-affairs/",
  "title": "Burning Man at the Conference on World Affairs",
  "author": "Will Chase",
  "dateISO": "2012-04-10T16:18:04-07:00",
  "content": "Fresh off her well-received (and lightning-speed) talk about Burning Man at The Economist’s Ideas Economy forum, we’re excited that Andie Grace is now representing Burning Man at the Conference on World Affairs, taking place this week at The University of Colorado, Boulder.\n\nAndie will be speaking on several interesting panels, but the most pertinent to Burners is the “Burning Man Women” panel with Burner/scientist Kiki Sanford this Friday at noon. The event is free and open to public … if you’re in the vicinity, head over there!\n\nHere’s more information about the conference (which Roger Ebert called “the conference on Everything Conceivable.”), and a video that’ll give you an idea of what it’s about:",
  "source": "burningman_journal",
  "category": "global-network",
  "topic": "global-programming"
}